video_summarizer/__init__.py
video_summarizer/__main__.py
video_summarizer/cli/__init__.py
video_summarizer/cli/main.py
video_summarizer/config/__init__.py
video_summarizer/config/constants.py
video_summarizer/config/settings.py
video_summarizer/core/__init__.py
video_summarizer/core/base.py
video_summarizer/resources/.env.example
video_summarizer/resources/__init__.py
video_summarizer/scraper/__init__.py
video_summarizer/scraper/downloader.py
video_summarizer/scraper/validator.py
video_summarizer/summarizer/__init__.py
video_summarizer/summarizer/chunker.py
video_summarizer/summarizer/preprocessor.py
video_summarizer/summarizer/summarizer.py
video_summarizer/transcriber/__init__.py
video_summarizer/transcriber/container.py
video_summarizer/transcriber/extractor.py
video_summarizer/transcriber/stats_monitor.py
video_summarizer/transcriber/transcriber.py
video_summarizer/utils/__init__.py
video_summarizer/utils/errors.py
video_summarizer/utils/gpu_checker.py
video_summarizer/utils/logging.py
video_summarizer/utils/types.py
vidscribe-0.1.6.dist-info/METADATA
vidscribe-0.1.6.dist-info/WHEEL
vidscribe-0.1.6.dist-info/entry_points.txt
vidscribe-0.1.6.dist-info/licenses/LICENSE.md
vidscribe-0.1.6.dist-info/RECORD
