Metadata-Version: 2.4
Name: vidscribe
Version: 0.1.6
Summary: CLI tool for automatic video summarization using Whisper and LLMs
Project-URL: Homepage, https://github.com/yeyuan98/video_summarizer
Project-URL: Repository, https://github.com/yeyuan98/video_summarizer
Project-URL: Issues, https://github.com/yeyuan98/video_summarizer/issues
Author: yeyuan98
License: CC-BY-NC-ND-4.0
License-File: LICENSE.md
Keywords: cli,summarization,transcription,video,whisper
Classifier: Development Status :: 3 - Alpha
Classifier: Intended Audience :: Developers
Classifier: Programming Language :: Python :: 3
Classifier: Programming Language :: Python :: 3.12
Requires-Python: >=3.12
Requires-Dist: click
Requires-Dist: docker
Requires-Dist: httpx
Requires-Dist: loguru
Requires-Dist: moviepy
Requires-Dist: mutagen
Requires-Dist: openai
Requires-Dist: pydantic
Requires-Dist: pydantic-settings
Requires-Dist: python-dotenv
Requires-Dist: rich-click
Requires-Dist: yt-dlp
